LICENSE.txt
MANIFEST.in
README.md
pyproject.toml
setup.cfg
setup.py
src/repast4py/SpatialTree.cpp
src/repast4py/SpatialTree.h
src/repast4py/__init__.py
src/repast4py/borders.h
src/repast4py/checkpoint.py
src/repast4py/context.py
src/repast4py/core.h
src/repast4py/core.py
src/repast4py/coremodule.cpp
src/repast4py/coremodule.h
src/repast4py/cspace.h
src/repast4py/distributed_space.cpp
src/repast4py/distributed_space.h
src/repast4py/geometry.cpp
src/repast4py/geometry.h
src/repast4py/geometry.py
src/repast4py/grid.h
src/repast4py/logging.py
src/repast4py/network.py
src/repast4py/occupancy.h
src/repast4py/parameters.py
src/repast4py/random.py
src/repast4py/schedule.py
src/repast4py/space.cpp
src/repast4py/space.h
src/repast4py/space.py
src/repast4py/space_types.h
src/repast4py/spacemodule.cpp
src/repast4py/types.h
src/repast4py/util.py
src/repast4py/value_layer.py
src/repast4py.egg-info/PKG-INFO
src/repast4py.egg-info/SOURCES.txt
src/repast4py.egg-info/dependency_links.txt
src/repast4py.egg-info/requires.txt
src/repast4py.egg-info/top_level.txt
tests/test_agents.py
tests/test_checkpoint.py
tests/test_schedule.py
tests/test_space.py
tests/test_value_layer.py