Metadata-Version: 2.4
Name: repast4py
Version: 1.2.1
Summary: repast4py package
Home-page: https://repast.github.io/repast4py.site/index.html
Author: Nick Collier
Author-email: ncollier@anl.gov
Maintainer: Nick Collier
Maintainer-email: ncollier@anl.gov
License: BSD 3-Clause License
Project-URL: Git Repostitory, https://github.com/Repast/repast4py
Project-URL: Issue Tracker, https://github.com/Repast/repast4py/issues
Project-URL: Documentation, https://repast.github.io/repast4py.site/guide/user_guide.html
Classifier: Development Status :: 4 - Beta
Classifier: Intended Audience :: Science/Research
Classifier: Operating System :: POSIX :: Linux
Classifier: Programming Language :: Python :: 3
Classifier: Programming Language :: Python :: 3.9
Classifier: Programming Language :: Python :: 3.10
Classifier: Programming Language :: Python :: 3.11
Classifier: Programming Language :: Python :: 3.12
Classifier: Programming Language :: Python :: 3.13
Classifier: Topic :: Scientific/Engineering
Classifier: Topic :: Software Development :: Libraries :: Python Modules
Classifier: Topic :: System :: Distributed Computing
Requires-Python: <3.14,>=3.9
License-File: LICENSE.txt
Requires-Dist: numpy
Requires-Dist: numba
Requires-Dist: mpi4py
Requires-Dist: torch
Requires-Dist: networkx>=2.6.2
Requires-Dist: pyyaml
Requires-Dist: Cython
Requires-Dist: typing_extensions; python_version < "3.8.0"
Requires-Dist: dill
Dynamic: license-file
Dynamic: summary
